pycltMath/__init__.py
pycltMath/calculator/__init__.py
pycltMath/calculator/calculator.py
pycltMath/year/__init__.py
pycltMath/year/math.py
pycltMath/year/math_operations.py
pycltmath-0.1.0.dist-info/licenses/LICENSE.txt
pycltmath-0.1.0.dist-info/METADATA
pycltmath-0.1.0.dist-info/WHEEL
pycltmath-0.1.0.dist-info/top_level.txt
pycltmath-0.1.0.dist-info/RECORD
